hoglet/__init__.py
hoglet-0.0.1.dist-info/METADATA
hoglet-0.0.1.dist-info/WHEEL
hoglet-0.0.1.dist-info/top_level.txt
hoglet-0.0.1.dist-info/RECORD
