Metadata-Version: 2.1
Name: hoglet
Version: 0.0.1
Summary: Hoglet
Classifier: Programming Language :: Python :: 3
Requires-Python: >=3.8
Provides-Extra: dev
Requires-Dist: build (~=0.9.0) ; extra == 'dev'
Requires-Dist: pytest (~=7.2.0) ; extra == 'dev'
Requires-Dist: pytest-cov (~=4.0.0) ; extra == 'dev'
Requires-Dist: pytest-xdist (~=3.1.0) ; extra == 'dev'
Requires-Dist: black (~=22.10.0) ; extra == 'dev'
Requires-Dist: isort (~=5.10.1) ; extra == 'dev'
Requires-Dist: autoflake (~=2.0.0) ; extra == 'dev'
Requires-Dist: twine (~=4.0.2) ; extra == 'dev'
